spotifython_cli.py
spotifython_cli-0.3.7.dist-info/licenses/LICENSE
spotifython_cli-0.3.7.dist-info/METADATA
spotifython_cli-0.3.7.dist-info/PKG-INFO.sync-conflict-20250324-124510-ASSDQ2C
spotifython_cli-0.3.7.dist-info/WHEEL
spotifython_cli-0.3.7.dist-info/entry_points.txt
spotifython_cli-0.3.7.dist-info/top_level.txt
spotifython_cli-0.3.7.dist-info/RECORD
