Metadata-Version: 2.4
Name: spotifython-cli
Version: 0.3.7
Summary: A command line interface for spotifython intended for use with spotifyd
Home-page: https://github.com/vawvaw/spotifython-cli
Author: VAWVAW
Author-email: vawvaw@vaw-valentin.de
License: GPLv3
Project-URL: Bug Tracker, https://github.com/vawvaw/spotifython-cli/issues
Classifier: Development Status :: 3 - Alpha
Classifier: Intended Audience :: End Users/Desktop
Classifier: Programming Language :: Python :: 3.10
Classifier: License :: OSI Approved :: GNU General Public License v3 (GPLv3)
Classifier: Natural Language :: English
Classifier: Operating System :: OS Independent
Classifier: Topic :: Internet
Classifier: Topic :: Utilities
Classifier: Typing :: Typed
Requires-Python: >=3.10
License-File: LICENSE
Requires-Dist: spotifython>=0.2.9
Requires-Dist: click
Dynamic: author
Dynamic: author-email
Dynamic: classifier
Dynamic: description
Dynamic: description-content-type
Dynamic: home-page
Dynamic: license
Dynamic: license-file
Dynamic: project-url
Dynamic: requires-dist
Dynamic: requires-python
Dynamic: summary
